chatteract/__init__.py
chatteract/handle_openai_response_and_execute_functions.py
chatteract/send_api_request.py
chatteract-0.6.dist-info/METADATA
chatteract-0.6.dist-info/WHEEL
chatteract-0.6.dist-info/top_level.txt
chatteract-0.6.dist-info/RECORD
