Metadata-Version: 2.1
Name: chatteract
Version: 0.6
Summary: A package to handle OpenAI responses and execute function calls.
Home-page: https://github.com/aspelund/chatter-act
Author: Mattias Aspelund
Classifier: Programming Language :: Python :: 3
Classifier: License :: OSI Approved :: MIT License
Classifier: Operating System :: OS Independent
Requires-Python: >=3.6
Requires-Dist: requests
Requires-Dist: tiktoken
